Metadata-Version: 1.0
Name: MacroPy
Version: 1.0.3
Summary: Macros for Python: Quasiquotes, Case Classes, LINQ and more!
Home-page: https://github.com/lihaoyi/macropy
Author: Li Haoyi, Justin Holmgren
Author-email: haoyi.sg@gmail.com, justin.holmgren@gmail.com
License: MIT
Platform: UNKNOWN
Classifier: Programming Language :: Python :: 2.7
